mcio_ctrl/__about__.py
mcio_ctrl/__init__.py
mcio_ctrl/cbor.py
mcio_ctrl/config.py
mcio_ctrl/controller.py
mcio_ctrl/envs/__init__.py
mcio_ctrl/envs/base_env.py
mcio_ctrl/envs/env_util.py
mcio_ctrl/envs/mcio_env.py
mcio_ctrl/envs/minerl_env.py
mcio_ctrl/gui.py
mcio_ctrl/instance.py
mcio_ctrl/mc_mock.py
mcio_ctrl/mcio_gui.py
mcio_ctrl/network.py
mcio_ctrl/py.typed
mcio_ctrl/resources/minerl_cursor_16x16.npy
mcio_ctrl/scripts/README.md
mcio_ctrl/scripts/mcio_cmd.py
mcio_ctrl/server.py
mcio_ctrl/types.py
mcio_ctrl/util.py
mcio_ctrl/world.py
mcio_ctrl-1.4.0.dist-info/WHEEL
mcio_ctrl-1.4.0.dist-info/entry_points.txt
mcio_ctrl-1.4.0.dist-info/METADATA
mcio_ctrl-1.4.0.dist-info/RECORD
