Metadata-Version: 2.4
Name: mcio-ctrl
Version: 1.4.0
Summary: Python interface to connect to the MCio Minecraft mod
Author: TwoTurtles
Author-email: TwoTurtles <97465192+twoturtles@users.noreply.github.com>
License-Expression: MIT
Classifier: Programming Language :: Python :: 3
Classifier: License :: OSI Approved :: MIT License
Classifier: Operating System :: OS Independent
Requires-Dist: pyzmq>=26.2.0
Requires-Dist: cbor2>=5.6.5
Requires-Dist: glfw>=2.7.0
Requires-Dist: pyopengl>=3.1.7
Requires-Dist: gymnasium>=1.0.0
Requires-Dist: pillow>=11.0.0
Requires-Dist: imageio>=2.37.0
Requires-Dist: imageio-ffmpeg>=0.6.0
Requires-Dist: minecraft-launcher-lib>=7.1
Requires-Dist: tqdm>=4.67.1
Requires-Dist: requests>=2.32.3
Requires-Dist: ruamel-yaml>=0.18.6
Requires-Dist: dacite>=1.8.1
Requires-Dist: nbt>=1.5.1
Requires-Python: >=3.12
Project-URL: Changelog, https://github.com/twoturtles/mcio_ctrl/blob/main/CHANGELOG.md
Project-URL: Issues, https://github.com/twoturtles/mcio_ctrl/issues
Project-URL: Source, https://github.com/twoturtles/mcio_ctrl
